{
  "name": "magic_realms:taverns/plains/signs",
  "fallback": "minecraft:empty",
  "elements": [
    {
      "weight": 1,
      "element": {
        "element_type": "minecraft:single_pool_element",
        "location": "magic_realms:taverns/plains/signs/elders_eye",
        "processors": "minecraft:empty",
        "projection": "rigid"
      }
    },
    {
      "weight": 1,
      "element": {
        "element_type": "minecraft:single_pool_element",
        "location": "magic_realms:taverns/plains/signs/familiars_end",
        "processors": "minecraft:empty",
        "projection": "rigid"
      }
    },
    {
      "weight": 1,
      "element": {
        "element_type": "minecraft:single_pool_element",
        "location": "magic_realms:taverns/plains/signs/hoglins_head",
        "processors": "minecraft:empty",
        "projection": "rigid"
      }
    },
    {
      "weight": 1,
      "element": {
        "element_type": "minecraft:single_pool_element",
        "location": "magic_realms:taverns/plains/signs/three_skulls",
        "processors": "minecraft:empty",
        "projection": "rigid"
      }
    },
    {
      "weight": 1,
      "element": {
        "element_type": "minecraft:single_pool_element",
        "location": "magic_realms:taverns/plains/signs/tired_deer",
        "processors": "minecraft:empty",
        "projection": "rigid"
      }
    }
  ]
}